wingman/__init__.py
wingman/cli_scripts.py
wingman/config.yaml
wingman/config_utils.py
wingman/exceptions.py
wingman/neural_blocks.py
wingman/print_utils.py
wingman/utils.py
wingman/wingman.py
jj_wingman-0.22.2.dist-info/LICENSE.txt
jj_wingman-0.22.2.dist-info/METADATA
jj_wingman-0.22.2.dist-info/WHEEL
jj_wingman-0.22.2.dist-info/entry_points.txt
jj_wingman-0.22.2.dist-info/top_level.txt
jj_wingman-0.22.2.dist-info/RECORD
