Metadata-Version: 2.1
Name: jj_wingman
Version: 0.22.2
Summary: Wingman library for AI projects.
Author-email: Jet <taijunjet@hotmail.com>
License: Copyright (c) 2018 The Python Packaging Authority
Project-URL: Homepage, https://github.com/jjshoots/Wingman
Keywords: Machine Learning
Classifier: Programming Language :: Python :: 3
Classifier: License :: OSI Approved :: MIT License
Classifier: Operating System :: OS Independent
Requires-Python: >=3.9
License-File: LICENSE.txt
Requires-Dist: numpy
Requires-Dist: wandb
Requires-Dist: pyyaml
Requires-Dist: prefetch-generator
